weao-1.0.0.dist-info/METADATA
weao-1.0.0.dist-info/WHEEL
weao-1.0.0.dist-info/licenses/AUTHORS.md
weao-1.0.0.dist-info/licenses/LICENSE
weao/__init__.py
weao/client.py
weao/constants.py
weao/errors.py
weao/exploit.py
weao/py.typed
weao/status.py
weao-1.0.0.dist-info/RECORD
