Metadata-Version: 2.1
Name: weao
Version: 1.0.0
Summary: Pythonic API Wrapper for WEAO API
Author: xFGhoul
License: MIT
Requires-Python: >=3.11
Requires-Dist: aiohttp>=3.8.4
Requires-Dist: humanize>=4.6.0
Requires-Dist: yarl>=1.8.2
